aiocassandra.py
aiocassandra-2.0.1.dist-info/DESCRIPTION.rst
aiocassandra-2.0.1.dist-info/LICENSE.txt
aiocassandra-2.0.1.dist-info/METADATA
aiocassandra-2.0.1.dist-info/RECORD
aiocassandra-2.0.1.dist-info/WHEEL
aiocassandra-2.0.1.dist-info/metadata.json
aiocassandra-2.0.1.dist-info/top_level.txt
