Metadata-Version: 2.0
Name: aiocassandra
Version: 2.0.1
Summary: Simple threaded cassandra wrapper for asyncio
Home-page: https://github.com/aio-libs/aiocassandra
Author: Victor Kovtun
Author-email: hellysmile@gmail.com
License: UNKNOWN
Keywords: cassandra,asyncio
Platform: UNKNOWN
Classifier: Development Status :: 5 - Production/Stable
Classifier: Intended Audience :: Developers
Classifier: License :: OSI Approved :: MIT License
Classifier: Operating System :: POSIX
Classifier: Operating System :: Microsoft :: Windows
Classifier: Programming Language :: Python
Classifier: Programming Language :: Python :: 3
Classifier: Programming Language :: Python :: 3.5
Classifier: Programming Language :: Python :: 3.6
Classifier: Framework :: AsyncIO
Requires-Python: >=3.4.0
Requires-Dist: cassandra-driver
Requires-Dist: async-generator
